kropp/__init__.py
kropp-0.1.3.dist-info/METADATA
kropp-0.1.3.dist-info/WHEEL
kropp-0.1.3.dist-info/entry_points.txt
kropp-0.1.3.dist-info/top_level.txt
kropp-0.1.3.dist-info/RECORD
